wmipa/__init__.py
wmipa/integrator.py
wmipa/latte_integrator.py
wmipa/log.py
wmipa/polytope.py
wmipa/praiseinference.py
wmipa/praiselang.py
wmipa/sympy2pysmt.py
wmipa/utils.py
wmipa/weights.py
wmipa/wmi.py
wmipa/wmiexception.py
wmipa/wmivariables.py
wmipa-0.1.5.dist-info/LICENSE.md
wmipa-0.1.5.dist-info/METADATA
wmipa-0.1.5.dist-info/WHEEL
wmipa-0.1.5.dist-info/top_level.txt
wmipa-0.1.5.dist-info/RECORD
