Metadata-Version: 2.1
Name: wmipa
Version: 0.1.5
Summary: Weighted Model Integration PA (Predicate Abstraction) solver.
Home-page: http://github.com/unitn-sml/wmi-pa
Author: Paolo Morettin
Author-email: paolo.morettin@unitn.it
License: MIT
Platform: UNKNOWN
Classifier: License :: OSI Approved :: MIT License
Classifier: Programming Language :: Python
Classifier: Programming Language :: Python :: 3
Requires-Python: >=3.5.0
Requires-Dist: networkx
Requires-Dist: numpy
Requires-Dist: pysmt
Requires-Dist: sympy
